{"ta-mes":"Marzo 2026","ta-resumen":"","ta-org-seguidores":"4753","ta-org-alcance":"1928","ta-org-engagement":"149","ta-p1-desc":"Post estilo chat problema/solución - Enchiladas","ta-p1-alcance":"130","ta-p1-engagement":"5","ta-p1-link":"https://www.instagram.com/p/DVZGvqDDTbR/?next=%2Fp%2FDVZGvqDDTbR%2F&img_index=1","ta-p2-desc":"Post interactivo de elige tu plato favorito del top 3","ta-p2-alcance":"120","ta-p2-engagement":"7","ta-p2-link":"https://www.instagram.com/p/DWJs9P3jUsv/?img_index=1","ta-p3-desc":"Post informativo de las versiones de Enichiladas del menú","ta-p3-alcance":"119","ta-p3-engagement":"12","ta-p3-link":"https://www.instagram.com/p/DVd_MtAja7x/?img_index=1","ta-camp1-nombre":"Informational: Promote Enchiladas","ta-camp1-fecha":"03/04/2026","ta-camp1-segmento":"Everyone","ta-camp1-enviados":"9856","ta-camp1-apertura":"45","ta-camp1-ctr":"0.33","ta-camp1-ventas":"4011","ta-camp2-nombre":"$10 Off your next purchase","ta-camp2-fecha":"03/09/2026","ta-camp2-segmento":"Lapsed Customer","ta-camp2-enviados":"8340","ta-camp2-apertura":"42","ta-camp2-ctr":"0.74","ta-camp2-ventas":"1257","ta-camp3-nombre":"$2off any Plato Tradicional","ta-camp3-fecha":"03/16/2026","ta-camp3-segmento":"Everyone","ta-camp3-enviados":"9857","ta-camp3-apertura":"41","ta-camp3-ctr":"0.32","ta-camp3-ventas":"3254","ta-camp4-nombre":"Informational: Promote Catering","ta-camp4-fecha":"03/26/2026","ta-camp4-segmento":"Everyone","ta-camp4-enviados":"9794","ta-camp4-apertura":"42","ta-camp4-ctr":"0.16","ta-camp4-ventas":"1143","ta-camp5-nombre":"","ta-camp5-fecha":"","ta-camp5-segmento":"","ta-camp5-enviados":"","ta-camp5-apertura":"","ta-camp5-ctr":"","ta-camp5-ventas":"","ta-analisis":""}